qualysapi/__init__.py
qualysapi/api_actions.py
qualysapi/api_methods.py
qualysapi/api_objects.py
qualysapi/config.py
qualysapi/connector.py
qualysapi/settings.py
qualysapi/util.py
qualysapi/version.py
qualysapi-8.1.0.dist-info/METADATA
qualysapi-8.1.0.dist-info/WHEEL
qualysapi-8.1.0.dist-info/license
qualysapi-8.1.0.dist-info/top_level.txt
qualysapi-8.1.0.dist-info/RECORD
