Metadata-Version: 2.1
Name: qualysapi
Version: 8.1.0
Summary: Qualys API Helper
Home-page: https://github.com/paragbaxi/qualysapi
Author: Parag Baxi
Author-email: parag.baxi@gmail.com
License: BSD-new
Project-URL: Bug Tracker, https://github.com/paragbaxi/qualysapi/issues
Project-URL: Source Code, https://github.com/paragbaxi/qualysapi
Keywords: Qualys,Qualys API
Classifier: Development Status :: 5 - Production/Stable
Classifier: Topic :: Utilities
Classifier: License :: OSI Approved :: Apache Software License
Classifier: Intended Audience :: Developers
Classifier: Programming Language :: Python :: 3.6
Classifier: Programming Language :: Python :: 3.7
Classifier: Programming Language :: Python :: 3.8
License-File: license
Requires-Dist: lxml
Requires-Dist: requests
